omni_python/__init__.py
omni_python/base.py
omni_python/client.py
omni_python/response.py
slang_omni-0.0.2.dist-info/METADATA
slang_omni-0.0.2.dist-info/WHEEL
slang_omni-0.0.2.dist-info/top_level.txt
slang_omni-0.0.2.dist-info/RECORD
